{
  "recentFiles": [
    {
      "basename": "3 Renderer Feature",
      "path": "引擎Unity3D/3 URP精粹/3 Renderer Feature.md"
    },
    {
      "basename": "2 URP",
      "path": "引擎Unity3D/3 URP精粹/2 URP.md"
    },
    {
      "basename": "图形学八股",
      "path": "图形学/面经/图形学八股.md"
    },
    {
      "basename": "04 纹理",
      "path": "图形学/1 图形系统/04 纹理.md"
    },
    {
      "basename": "03 光追理论",
      "path": "图形学/3 全局光照GI/03 光追理论.md"
    },
    {
      "basename": "09 阴影",
      "path": "图形学/1 图形系统/09 阴影.md"
    },
    {
      "basename": "03 光照向量",
      "path": "图形学/0 3D数学/公式推导/03 光照向量.md"
    },
    {
      "basename": "05 射线相交",
      "path": "图形学/0 3D数学/公式推导/05 射线相交.md"
    },
    {
      "basename": "3D数学",
      "path": "图形学/0 3D数学/3D数学.md"
    },
    {
      "basename": "01 三维旋转",
      "path": "图形学/0 3D数学/公式推导/01 三维旋转.md"
    },
    {
      "basename": "02 空间变换",
      "path": "图形学/0 3D数学/公式推导/02 空间变换.md"
    },
    {
      "basename": "6 纹理化",
      "path": "图形学/4 书籍/《RTR4》/6 纹理化.md"
    },
    {
      "basename": "02 光栅化",
      "path": "图形学/1 图形系统/02 光栅化.md"
    },
    {
      "basename": "Chapter 6 Texturing 纹理",
      "path": "图形学/4 书籍/RTR4社区版/Chapter 6 Texturing 纹理.md"
    },
    {
      "basename": "技术向",
      "path": "图形学/面经/技术向.md"
    },
    {
      "basename": "总结",
      "path": "图形学/6 软渲染器/软光栅/总结.md"
    },
    {
      "basename": "透视矫正插值",
      "path": "图形学/6 软渲染器/软光栅/透视矫正插值.md"
    },
    {
      "basename": "TinyRenderer",
      "path": "图形学/6 软渲染器/软光栅/TinyRenderer.md"
    },
    {
      "basename": "03 光照模型",
      "path": "图形学/1 图形系统/03 光照模型.md"
    },
    {
      "basename": "FFT代码实现",
      "path": "技术美术/5 水体渲染/FFT海洋/FFT代码实现.md"
    },
    {
      "basename": "02 PBR理论",
      "path": "图形学/3 全局光照GI/02 PBR理论.md"
    },
    {
      "basename": "04 PBR推导",
      "path": "图形学/3 全局光照GI/PBR实战/PBR相关/04 PBR推导.md"
    },
    {
      "basename": "TA101",
      "path": "引擎Unity3D/2 Shader精粹/《Built-in》/TA101.md"
    },
    {
      "basename": "ASE",
      "path": "引擎Unity3D/2 Shader精粹/《Built-in》/ASE.md"
    },
    {
      "basename": "5 CommandBuffer",
      "path": "引擎Unity3D/3 URP精粹/5 CommandBuffer.md"
    },
    {
      "basename": "02 Bloom",
      "path": "技术美术/3 后处理/02 Bloom.md"
    },
    {
      "basename": "01 光学原理",
      "path": "图形学/3 全局光照GI/PBR实战/PBR相关/01 光学原理.md"
    },
    {
      "basename": "庄懂AP01",
      "path": "引擎Unity3D/2 Shader精粹/《Built-in》/庄懂AP01.md"
    },
    {
      "basename": "CG shaderlab",
      "path": "引擎Unity3D/2 Shader精粹/《Built-in》/CG shaderlab.md"
    },
    {
      "basename": "死亡搁浅扫描特效",
      "path": "引擎Unity3D/收藏夹/死亡搁浅扫描特效.md"
    },
    {
      "basename": "卡通水",
      "path": "技术美术/5 水体渲染/卡通水.md"
    },
    {
      "basename": "百人计划水体渲染【乱】",
      "path": "技术美术/5 水体渲染/百人计划水体渲染【乱】.md"
    },
    {
      "basename": "真实感水体渲染",
      "path": "技术美术/5 水体渲染/真实感水体渲染.md"
    },
    {
      "basename": "一波江水动京城：游戏水面渲染与互动",
      "path": "技术美术/5 水体渲染/一波江水动京城：游戏水面渲染与互动.md"
    },
    {
      "basename": "FFT理论",
      "path": "技术美术/5 水体渲染/FFT海洋/FFT理论.md"
    },
    {
      "basename": "02 顶点动画",
      "path": "技术美术/1 渲染雅集/02 顶点动画.md"
    },
    {
      "basename": "06 雾",
      "path": "技术美术/1 渲染雅集/06 雾.md"
    },
    {
      "basename": "05 故障Glitch",
      "path": "技术美术/3 后处理/05 故障Glitch.md"
    },
    {
      "basename": "01 图像模糊",
      "path": "技术美术/3 后处理/01 图像模糊.md"
    },
    {
      "basename": "03 景深",
      "path": "技术美术/3 后处理/03 景深.md"
    },
    {
      "basename": "Unity URP 实现 SSAO",
      "path": "技术美术/3 后处理/SSAO/Unity URP 实现 SSAO.md"
    },
    {
      "basename": "04 溶解",
      "path": "技术美术/1 渲染雅集/04 溶解.md"
    },
    {
      "basename": "05 描边",
      "path": "技术美术/1 渲染雅集/05 描边.md"
    },
    {
      "basename": "03 UV操作",
      "path": "技术美术/1 渲染雅集/03 UV操作.md"
    },
    {
      "basename": "03 深度法线纹理",
      "path": "技术美术/1 渲染雅集/03 深度法线纹理.md"
    },
    {
      "basename": "01 Trick！",
      "path": "技术美术/1 渲染雅集/01 Trick！.md"
    },
    {
      "basename": "06 深度测试",
      "path": "图形学/1 图形系统/06 深度测试.md"
    },
    {
      "basename": "URP 渲染优化总结",
      "path": "引擎Unity3D/2 Shader精粹/《渲染优化》/URP 渲染优化总结.md"
    },
    {
      "basename": "01 渲染管线",
      "path": "图形学/1 图形系统/01 渲染管线.md"
    },
    {
      "basename": "10 色彩",
      "path": "图形学/1 图形系统/10 色彩.md"
    }
  ],
  "omittedPaths": [],
  "maxLength": null,
  "openType": "tab"
}